simuldb-0.12.3.dist-info/METADATA
simuldb-0.12.3.dist-info/WHEEL
simuldb/__init__.py
simuldb/simuldb.abi3.so
simuldb-0.12.3.dist-info/RECORD
