Metadata-Version: 2.1
Name: simuldb
Version: 0.12.3
Classifier: Programming Language :: Rust
Classifier: Topic :: Database
Summary: Database with backend and format agnostic data storage for simulation results coupled with metadata
Author: Daniel Hauck <mail@dhauck.eu>
Author-email: Daniel Hauck <mail@dhauck.eu>
License: MIT OR Apache-2.0
Project-URL: Documentation, https://solidtux-rust.gitlab.io/simuldb
